pyrokinetics/__init__.py
pyrokinetics/__main__.py
pyrokinetics/_version.py
pyrokinetics/constants.py
pyrokinetics/dataset_wrapper.py
pyrokinetics/decorators.py
pyrokinetics/factory.py
pyrokinetics/file_utils.py
pyrokinetics/local_species.py
pyrokinetics/metadata.py
pyrokinetics/normalisation.py
pyrokinetics/numerics.py
pyrokinetics/plugins.py
pyrokinetics/pyro.py
pyrokinetics/pyroscan.py
pyrokinetics/species.py
pyrokinetics/templates.py
pyrokinetics/typing.py
pyrokinetics/units.py
pyrokinetics/cli/__init__.py
pyrokinetics/cli/convert.py
pyrokinetics/cli/entrypoint.py
pyrokinetics/cli/generate.py
pyrokinetics/databases/__init__.py
pyrokinetics/databases/imas.py
pyrokinetics/diagnostics/__init__.py
pyrokinetics/diagnostics/saturation_rules.py
pyrokinetics/diagnostics/synthetic_highk_dbs.py
pyrokinetics/equilibrium/__init__.py
pyrokinetics/equilibrium/equilibrium.py
pyrokinetics/equilibrium/flux_surface.py
pyrokinetics/equilibrium/gacode.py
pyrokinetics/equilibrium/geqdsk.py
pyrokinetics/equilibrium/imas.py
pyrokinetics/equilibrium/transp.py
pyrokinetics/equilibrium/utils.py
pyrokinetics/gk_code/__init__.py
pyrokinetics/gk_code/cgyro.py
pyrokinetics/gk_code/gene.py
pyrokinetics/gk_code/gk_input.py
pyrokinetics/gk_code/gk_output.py
pyrokinetics/gk_code/gkw.py
pyrokinetics/gk_code/gs2.py
pyrokinetics/gk_code/gx.py
pyrokinetics/gk_code/ids.py
pyrokinetics/gk_code/stella.py
pyrokinetics/gk_code/tglf.py
pyrokinetics/kinetics/__init__.py
pyrokinetics/kinetics/gacode.py
pyrokinetics/kinetics/imas.py
pyrokinetics/kinetics/jetto.py
pyrokinetics/kinetics/kinetics.py
pyrokinetics/kinetics/pfile.py
pyrokinetics/kinetics/scene.py
pyrokinetics/kinetics/transp.py
pyrokinetics/local_geometry/__init__.py
pyrokinetics/local_geometry/fourier_cgyro.py
pyrokinetics/local_geometry/fourier_gene.py
pyrokinetics/local_geometry/local_geometry.py
pyrokinetics/local_geometry/metric.py
pyrokinetics/local_geometry/miller.py
pyrokinetics/local_geometry/miller_turnbull.py
pyrokinetics-0.8.0.dist-info/licenses/LICENSE
pyrokinetics-0.8.0.dist-info/METADATA
pyrokinetics-0.8.0.dist-info/WHEEL
pyrokinetics-0.8.0.dist-info/entry_points.txt
pyrokinetics-0.8.0.dist-info/top_level.txt
pyrokinetics-0.8.0.dist-info/RECORD
