Metadata-Version: 2.4
Name: pyrokinetics
Version: 0.8.0
Summary: Python package for running and analysing gyrokinetic simulations
Author-email: Bhavin Patel <bhavin.s.patel@ukaea.uk>
License:   GNU LESSER GENERAL PUBLIC LICENSE
Project-URL: Source, https://github.com/pyro-kinetics/pyrokinetics
Project-URL: Tracker, https://github.com/pyro-kinetics/pyrokinetics/issues
Project-URL: Documentation, https://pyrokinetics.readthedocs.io/en/latest/
Keywords: gyrokinetics,analysis,plasma,research
Classifier: Programming Language :: Python
Classifier: Development Status :: 3 - Alpha
Classifier: Natural Language :: English
Classifier: Intended Audience :: Science/Research
Classifier: License :: OSI Approved :: GNU Lesser General Public License v3 or later (LGPLv3+)
Classifier: Operating System :: OS Independent
Classifier: Programming Language :: Python
Classifier: Topic :: Software Development :: Libraries :: Python Modules
Classifier: Topic :: Scientific/Engineering :: Physics
Requires-Python: >=3.10
License-File: LICENSE
Requires-Dist: numpy<=2.1.0,>=1.20.3
Requires-Dist: matplotlib>=3.3.4
Requires-Dist: f90nml>=1.4.2
Requires-Dist: scipy>=1.10.1
Requires-Dist: h5py>=2.10
Requires-Dist: netCDF4>=1.5.6
Requires-Dist: path>=15.1.2
Requires-Dist: wheel>=0.36
Requires-Dist: freeqdsk~=0.5.0
Requires-Dist: cleverdict>=1.9.1
Requires-Dist: xarray<=2024.11.0,>=0.10
Requires-Dist: pint~=0.23
Requires-Dist: pint-xarray==0.4
Requires-Dist: contourpy~=1.0
Requires-Dist: xrft>=1.0.0
Requires-Dist: idspy-dictionaries==34000.2.0
Requires-Dist: idspy-toolkit==0.6.5
Requires-Dist: pyloidal~=0.2.0
Requires-Dist: xmltodict~=0.13.0
Requires-Dist: typing-extensions>=4.6.0
Requires-Dist: simplejson>=3.17.6
Requires-Dist: jetto-tools
Requires-Dist: setuptools; python_version >= "3.12"
Requires-Dist: periodictable
Requires-Dist: toml
Requires-Dist: sympy
Requires-Dist: shapely
Provides-Extra: docs
Requires-Dist: sphinx>=5.3; extra == "docs"
Requires-Dist: sphinx_autodoc_typehints>=1.19; extra == "docs"
Requires-Dist: sphinx-book-theme>=0.4.0rc1; extra == "docs"
Requires-Dist: myst_parser>=0.14.0; extra == "docs"
Provides-Extra: tests
Requires-Dist: pytest>=3.3.0; extra == "tests"
Requires-Dist: pytest-cov; extra == "tests"
Requires-Dist: pyrokinetics-plugin-examples==0.2.1; extra == "tests"
Provides-Extra: linting
Requires-Dist: black; extra == "linting"
Requires-Dist: isort; extra == "linting"
Requires-Dist: flake8; extra == "linting"
Dynamic: license-file
